CodeLingo/CodeLingo.py
CodeLingo/__init__.py
codelingo-0.1.dist-info/LICENSE.txt
codelingo-0.1.dist-info/METADATA
codelingo-0.1.dist-info/WHEEL
codelingo-0.1.dist-info/top_level.txt
codelingo-0.1.dist-info/RECORD
