Metadata-Version: 2.1
Name: codelingo
Version: 0.1
Summary: A library to convert code snippets into plain English.
Home-page: https://github.com/AshishGhodvinde/CodeLingo
Author: Taksh Kamble/Sahil Patil/Ashish Ghodvinde/Bhishek Zope
Author-email: ghodvindeashish@gmail.com
Classifier: Programming Language :: Python :: 3
Classifier: License :: OSI Approved :: MIT License
Classifier: Operating System :: OS Independent
Requires-Python: >=3.6
License-File: LICENSE.txt
